{
	"0": {
		"ROOM": [
			[[ 1010, 10, 0 ], [ 1640, 640, 350 ], { "idx": 1, "room_enter": "yes"} ],
			[[ 1010, 1270, 0 ], [ 1640, 1920, 350 ], { "idx": 3, "room_enter": "yes"} ],
			[[ 1010, 1920, 0 ], [ 1640, 2530, 350 ], { "idx": 4, "room_enter": "yes"} ],
			[[ 1640, 10, 0 ], [ 2255, 640, 350 ], { "idx": 6, "room_enter": "yes"} ],
			[[ 1640, 1920, 0 ], [ 2255, 2530, 350 ], { "idx": 9, "room_enter": "yes"} ],
			[[ 2255, 10, 0 ], [ 2855, 640, 350 ], { "idx": 10, "room_enter": "yes"} ],
			[[ 2255, 1920, 0 ], [ 2855, 2530, 350 ], { "idx": 13, "room_enter": "yes"} ],
			[[ 2855, 10, 0 ], [ 3490, 640, 350 ], { "idx": 14, "room_enter": "yes"} ],
			[[ 2855, 640, 0 ], [ 3490, 1270, 350 ], { "idx": 15, "room_enter": "yes"} ],
			[[ 2855, 1920, 0 ], [ 3490, 2530, 350 ], { "idx": 17, "room_enter": "yes"} ],
			[[ 3490, 10, 0 ], [ 4165, 640, 350 ], { "idx": 18, "room_enter": "no"} ],
			[[ 3490, 640, 0 ], [ 4165, 1270, 350 ], { "idx": 19, "room_enter": "yes"} ],
			[[ 3490, 1920, 0 ], [ 4165, 2530, 350 ], { "idx": 20, "room_enter": "yes"} ],
			[[ 4805, 10, 0 ], [ 5385, 640, 350 ], { "idx": 22, "room_enter": "yes"} ],
			[[ 4805, 640, 0 ], [ 5385, 1270, 350 ], { "idx": 23, "room_enter": "yes"} ],
			[[ 4805, 1270, 0 ], [ 5385, 1920, 350 ], { "idx": 24, "room_enter": "yes"} ],
			[[ 4805, 1920, 0 ], [ 5385, 2530, 350 ], { "idx": 25, "room_enter": "yes"} ]
		],
		"COR": [
			[[ 1010, 640, 0 ], [ 1640, 1270, 350 ], { "idx": 2, "room_enter": "yes"} ],
			[[ 1010, 2530, 0 ], [ 5385, 3075, 350 ], { "idx": 5, "room_enter": "yes"} ],
			[[ 1640, 640, 0 ], [ 2255, 1270, 350 ], { "idx": 7, "room_enter": "yes"} ],
			[[ 1640, 1270, 0 ], [ 2255, 1920, 350 ], { "idx": 8, "room_enter": "yes"} ],
			[[ 2255, 1270, 0 ], [ 2855, 1920, 350 ], { "idx": 12, "room_enter": "yes"} ],
			[[ 2855, 1270, 0 ], [ 4165, 1920, 350 ], { "idx": 16, "room_enter": "no"} ],
			[[ 4165, 10, 0 ], [ 4805, 2530, 350 ], { "idx": 21, "room_enter": "yes"} ]
		],
		"DOOR": [
			[[ 1230, 2514, 0 ], [ 1320, 2546, 200 ], { "idx": 1, "exit_type": "auto"} ],
			[[ 1250, 1904, 0 ], [ 1340, 1936, 200 ], { "idx": 2, "exit_type": "auto"} ],
			[[ 1624, 125, 0 ], [ 1656, 215, 200 ], { "idx": 3, "exit_type": "auto"} ],
			[[ 1624, 496, 0 ], [ 1656, 586, 200 ], { "idx": 4, "exit_type": "auto"} ],
			[[ 1624, 705, 0 ], [ 1656, 795, 200 ], { "idx": 5, "exit_type": "auto"} ],
			[[ 1624, 1580, 0 ], [ 1656, 1670, 200 ], { "idx": 6, "exit_type": "auto"} ],
			[[ 1624, 2235, 0 ], [ 1656, 2325, 200 ], { "idx": 7, "exit_type": "auto"} ],
			[[ 1725, 1254, 0 ], [ 1815, 1286, 200 ], { "idx": 8, "exit_type": "auto"} ],
			[[ 1870, 2514, 0 ], [ 1960, 2546, 200 ], { "idx": 9, "exit_type": "auto"} ],
			[[ 1945, 624, 0 ], [ 2035, 656, 200 ], { "idx": 10, "exit_type": "auto"} ],
			[[ 2239, 134, 0 ], [ 2271, 224, 200 ], { "idx": 11, "exit_type": "auto"} ],
			[[ 2239, 520, 0 ], [ 2271, 610, 200 ], { "idx": 12, "exit_type": "auto"} ],
			[[ 2239, 920, 0 ], [ 2271, 1010, 200 ], { "idx": 13, "exit_type": "auto"} ],
			[[ 2239, 1710, 0 ], [ 2271, 1800, 200 ], { "idx": 14, "exit_type": "auto"} ],
			[[ 2239, 2250, 0 ], [ 2271, 2340, 200 ], { "idx": 15, "exit_type": "auto"} ],
			[[ 2575, 624, 0 ], [ 2665, 656, 200 ], { "idx": 16, "exit_type": "auto"} ],
			[[ 2839, 360, 0 ], [ 2871, 450, 200 ], { "idx": 17, "exit_type": "auto"} ],
			[[ 2839, 920, 0 ], [ 2871, 1010, 200 ], { "idx": 18, "exit_type": "auto"} ],
			[[ 2839, 1580, 0 ], [ 2871, 1670, 200 ], { "idx": 19, "exit_type": "auto"} ],
			[[ 2839, 2245, 0 ], [ 2871, 2335, 200 ], { "idx": 20, "exit_type": "auto"} ],
			[[ 3095, 624, 0 ], [ 3185, 656, 200 ], { "idx": 21, "exit_type": "auto"} ],
			[[ 3100, 1254, 0 ], [ 3190, 1286, 200 ], { "idx": 22, "exit_type": "auto"} ],
			[[ 3474, 400, 0 ], [ 3506, 490, 200 ], { "idx": 23, "exit_type": "auto"} ],
			[[ 3474, 895, 0 ], [ 3506, 985, 200 ], { "idx": 24, "exit_type": "auto"} ],
			[[ 3474, 2245, 0 ], [ 3506, 2335, 200 ], { "idx": 25, "exit_type": "auto"} ],
			[[ 3720, 1254, 0 ], [ 3810, 1286, 200 ], { "idx": 26, "exit_type": "auto"} ],
			[[ 3755, 624, 0 ], [ 3845, 656, 200 ], { "idx": 27, "exit_type": "auto"} ],
			[[ 3755, 1904, 0 ], [ 3845, 1936, 200 ], { "idx": 28, "exit_type": "auto"} ],
			[[ 3775, 2514, 0 ], [ 3865, 2546, 200 ], { "idx": 29, "exit_type": "auto"} ],
			[[ 4149, 335, 0 ], [ 4181, 425, 200 ], { "idx": 30, "exit_type": "auto"} ],
			[[ 4149, 840, 0 ], [ 4181, 930, 200 ], { "idx": 31, "exit_type": "auto"} ],
			[[ 4149, 2200, 0 ], [ 4181, 2290, 200 ], { "idx": 32, "exit_type": "auto"} ],
			[[ 4420, 2514, 0 ], [ 4510, 2546, 200 ], { "idx": 33, "exit_type": "auto"} ],
			[[ 4789, 350, 0 ], [ 4821, 440, 200 ], { "idx": 34, "exit_type": "auto"} ],
			[[ 4789, 1655, 0 ], [ 4821, 1745, 200 ], { "idx": 35, "exit_type": "auto"} ],
			[[ 4789, 2260, 0 ], [ 4821, 2350, 200 ], { "idx": 36, "exit_type": "auto"} ],
			[[ 5025, 1254, 0 ], [ 5115, 1286, 200 ], { "idx": 37, "exit_type": "auto"} ],
			[[ 5035, 624, 0 ], [ 5125, 656, 200 ], { "idx": 38, "exit_type": "auto"} ]
		],
		"HOLE": [ ],
		"WIN": [ ],
		"STAI": [
			[[ 2255, 640, 0 ], [ 2855, 1270, 350 ], { "idx": 11, "room_enter": "no"} ]
		],
		"HALL": [ ],
		"DCLOSER": [ ],
		"DELECTR": [ ],
		"OBST": [
			[[ 1792, 26, 0 ], [ 1838, 191, 100 ], { "idx": 1 } ]
		],
		"VVENT": [ ],
		"MVENT": [ ],
		"EVACUEE": [
			[[ 1895, 140, 0 ], [ 1895, 140, 50 ], { "idx": 2 } ],
			[[ 5202, 2311, 0 ], [ 5202, 2311, 50 ], { "idx": 3 } ],
			[[ 4000, 1000, 50 ], [ 4000, 1000, 50 ], { "idx": 4 } ],
			[[ 1300, 2178, 50 ], [ 1300, 2178, 50 ], { "idx": 5 } ]
		],
		"FIRE": [ ]
	}
}
